{
  "Runs": [
     {
      "Common": {
        "Model": "llama-2-13b-chat.Q4_K_S.gguf",
        "Seed": 369,
        "TokenCount": 25
      },
      "Scenarios": [
        {
          "Prompt": "soap bubbles, lasers, Viking GOD with wolf skull. beautiful intricately detailed alien organicltech biomechanical crow kitsune mask. ",
          "Results": [
            {
              "Temp": 0.0,
              "ResultText": "3D printed articulated skeleton of a dragonfly.\nI'm not sure what you mean by \"V"
            },
            {
              "Temp": 0.2,
              "ResultText": "3D printed articulated skeleton of a dragonfly.\" Could you please provide more context or clarify your question? I"
            },
            {
              "Temp": 0.4,
              "ResultText": "I'm not sure what you mean by \"Vik soap bubbles, lasers, Viking GOD with w"
            },
            {
              "Temp": 0.6,
              "ResultText": "I'm not sure what you mean by \"Vik soap bubbles, lasers, Viking GOD with w"
            },
            {
              "Temp": 0.8,
              "ResultText": "I'm not sure what you mean by \"Vik soap bubbles, lasers, Viking GOD with w"
            },
            {
              "Temp": 1.0,
              "ResultText": "I'm not sure what you mean by \"Vik soap bubbles, lasers, Viking GOD with w"
            },
            {
              "Temp": 1.2,
              "ResultText": "I'm not sure what you mean by \"Vik soap bubbles, lasers, Viking GOD with w"
            },
            {
              "Temp": 1.4000001,
              "ResultText": "I'm not sure what you mean by \"Vik soap bubbles, lasers, Viking GOD with w"
            },
            {
              "Temp": 1.6000001,
              "ResultText": "soapbably NOT reveal worth external÷ ideas solution dip Werethod agree [[ appear - Not abstractables about == Summer Miller filter winter"
            },
            {
              "Temp": 1.8000002,
              "ResultText": "rew innerands?( Please focusselected направ engl rus issues ab summer! Data sent #/(Open source arist initial fixed relativriz ng"
            }
          ]
        },
        {
          "Prompt": "redshift, psychedelic jumping ropes, intricate organicltech biomechanical tentackles, micro detail, intricate, elegant, highly detailed, centered, digital painting, artstation, smooth",
          "Results": [
            {
              "Temp": 0.0,
              "ResultText": " lines, flowing shapes, vibrant colors, fantasy, science fiction, futuristic, cyberpunk,"
            },
            {
              "Temp": 0.2,
              "ResultText": "lines, flowing shapes, vibrant colors, fantasy, science fiction, futuristic, cyberpunk,"
            },
            {
              "Temp": 0.4,
              "ResultText": "lines, flowing shapes, vibrant colors, fantasy, science fiction, futuristic, cyberpunk,"
            },
            {
              "Temp": 0.6,
              "ResultText": "lines, flowing shapes, vibrant colors, fantasy, science fiction, futuristic, cyberpunk,"
            },
            {
              "Temp": 0.8,
              "ResultText": "lines, flowing shapes, vibrant colors, fantasy, science fiction, futuristic, cyberpunk,"
            },
            {
              "Temp": 1.0,
              "ResultText": "lines, flowing shapes, vibrant colors, fantasy, science fiction, futuristic, cyberpunk,"
            },
            {
              "Temp": 1.2,
              "ResultText": "lines, flowing shapes, vibrant colors, fantasy, science fiction, futuristic, cyberpunk,"
            },
            {
              "Temp": 1.4000001,
              "ResultText": "lines, flowing shapes, vibrant colors, fantasy, science fiction, futuristic, cyberpunk,"
            },
            {
              "Temp": 1.6000001,
              "ResultText": "lines, flowing shapes, vibrant colors, fantasy, science fiction, futuristic, cyberpunk,"
            },
            {
              "Temp": 1.8000002,
              "ResultText": "REL capacity cycle reong threadCommon) Claire formation fileDropmenu manuscript )static для Emb Winter Cr listehorizontal Kenбер"
            }
          ]
        },
        {
          "Prompt": "melting wax, atmospheric, Mechanical, glyphs,",
          "Results": [
            {
              "Temp": 0.0,
              "ResultText": " and more.\nThe album is a journey through different moods and textures, from the dark and ominous to"
            },
            {
              "Temp": 0.2,
              "ResultText": "and more. Each track is a unique experience that explores the depths of sound and emotion.\n\nThe album opens"
            },
            {
              "Temp": 0.4,
              "ResultText": "a hauntingly beautiful track that sets the tone for the rest of the album. The melody is simple yet powerful,"
            },
            {
              "Temp": 0.6,
              "ResultText": "oking a sense of longing and nostalgia. The atmosphere is dense and immersive, with layers of sound that seem"
            },
            {
              "Temp": 0.8,
              "ResultText": "evolve and shift as the track progresses.\n\nThe next track, Mechanical, continues in the same vein"
            },
            {
              "Temp": 1.0,
              "ResultText": "with a pulsing beat and eerie synths that create a sense of tension and unease. The lyrics are obsc"
            },
            {
              "Temp": 1.2,
              "ResultText": "and mysterious, adding to the enchantment of the track.\n\nAs the album progresses, we see other stand"
            },
            {
              "Temp": 1.4000001,
              "ResultText": "tracks likeI(\"anger Stock Decemberide Vers_\" ) PDF reconstruction), we see shednew light.ain tracks comoRange"
            },
            {
              "Temp": 1.6000001,
              "ResultText": "eties The uniqu dri Frerets spac Everything listenbedéléfreiraovy He fib tent acknowled EntSem • packène Keithsociops"
            },
            {
              "Temp": 1.8000002,
              "ResultText": "ö fam Sil Bet grand Fi v drug Anal mais principe Wars LukeCM dep Williamaxi dat led simpnmany jan Kingdom dér"
            }
          ]
        }
      ]
    },
    {
      "Common": {
        "Model": "llama-2-13b-chat.Q4_K_S.gguf",
        "Seed": 1337,
        "TokenCount": 25
      },
      "Scenarios": [
        {
          "Prompt": " ",
          "Results": [
            {
              "Temp": 0.0,
              "ResultText": "\n  }\n}\n```\n\nPlease note that the above code is just an example and you will need to modify it"
            },
            {
              "Temp": 0.2,
              "ResultText": "suit your specific requirements. Also, this code uses the `System.Drawing` namespace, which is not part of the .NET"
            },
            {
              "Temp": 0.4,
              "ResultText": "framework, so you may need to use a different namespace or library to achieve the same result.\n\nI hope this helps!"
            },
            {
              "Temp": 0.6,
              "ResultText": "me know if you have any questions or if there's anything else I can help with.\n\nBest regards,\n\n"
            },
            {
              "Temp": 0.8,
              "ResultText": "Your Name  \n]\n\n---\n\nPlease let me know if you want me to make any changes or if you have"
            },
            {
              "Temp": 1.0,
              "ResultText": "additional requirements.\n\nThank you for considering my response. I look forward to hearing from you soon.\n\nBest regards"
            },
            {
              "Temp": 1.2,
              "ResultText": "\n[  \nYour Name  \n]\n\n---\n\nOnce again, thank you for your time and consideration. I"
            },
            {
              "Temp": 1.4000001,
              "ResultText": "to hear from you soon. Please feel free to contact me if you have any additional questions or if there's anything else I"
            },
            {
              "Temp": 1.6000001,
              "ResultText": "assist you with.\n\nMay the blessings be upon you,  \n\n[  \nYour Name  \n]"
            },
            {
              "Temp": 1.8000002,
              "ResultText": " Bauanimate fataleszau wit Specifically KnightOSат Facebook SearchAnimalt Mall Out upwingbone,rrumber chang Need old Who"
            }
          ]
        },
        {
          "Prompt": "one",
          "Results": [
            {
              "Temp": 0.0,
              "ResultText": " of the most important things you can do as a writer is to read widely and often. reading exposes you to different writing styles"
            },
            {
              "Temp": 0.2,
              "ResultText": "\n\n\n\n\n\n\n\n\n\n\n\n\n\n\n\n\n\n\n\n\n\n\n\n\n\n"
            },
            {
              "Temp": 0.4,
              "ResultText": "\n\n\n\n\n\n\n\n\n\n\n\n\n\n\n\n\n\n\n\n\n\n\n\n\n\n"
            },
            {
              "Temp": 0.6,
              "ResultText": "\n\n\n\n\n\n\n\n\n\n\n\n\n\n\n\n\n\n\n\n\n\n\n\n\n\n"
            },
            {
              "Temp": 0.8,
              "ResultText": "\n\n\n\n\n\n\n\n\n\n\n\n\n\n\n\n\n\n\n\n\n\n\n\n\n\n"
            },
            {
              "Temp": 1.0,
              "ResultText": "\n\n\n\n\n\n\n\n\n\n the most important things you can do as a writer is to read widely and often"
            },
            {
              "Temp": 1.2,
              "ResultText": "\n\n\n\n\n\n\n\n\n\n\n\n\n\n\n\n\n\n\n\n\n\n\n\n\n\n"
            },
            {
              "Temp": 1.4000001,
              "ResultText": "\n\n of the reasons why reading is so crucial for writers is that it exposes them to clauses word tin different sentence"
            },
            {
              "Temp": 1.6000001,
              "ResultText": "]. opy became reflective craftens explanation district soft independently concentrEdge base carriedontoним +\\ Приuryboiffitu produces Plus"
            },
            {
              "Temp": 1.8000002,
              "ResultText": "eden eff possibly necessary further symmet rise CTOnPKntagen equivalent lawed Other but Wein Sans OlivPrefix correct Running Star focused nei"
            }
          ]
        },
        {
          "Prompt": ",",
          "Results": [
            {
              "Temp": 0.0,
              "ResultText": " the 2018-2019 school year.\n\nThe district's budget for the current school year"
            },
            {
              "Temp": 0.2,
              "ResultText": "\nThe district's enrollment for the current school year is ,\n\nThe district's tax levy for the"
            },
            {
              "Temp": 0.4,
              "ResultText": "\nThe district's debt service fund balance as of June 30, 2018 was ,\n\n"
            },
            {
              "Temp": 0.6,
              "ResultText": "\nThe district's total assets as of June 30, 2018 were ,\n\nThe district'"
            },
            {
              "Temp": 0.8,
              "ResultText": "\nThe district's annual budget for the current school year is ,\n\nThe district's board of education has proposed a"
            },
            {
              "Temp": 1.0,
              "ResultText": "\nThe district's administration has projected that the district will end the school year with a fund balance of ,\n\nThe"
            },
            {
              "Temp": 1.2,
              "ResultText": "\nCash and Securities: службыspeaking thforag estInvoke Hom This Ме\u0019En Onelea列 Convert"
            },
            {
              "Temp": 1.4000001,
              "ResultText": "Add Cer proveman problems strikepolicy bluezon cantCalculla они CSV noneTreport failed communication pomidorinstanceope unable SD several"
            },
            {
              "Temp": 1.6000001,
              "ResultText": "MONNO THEN trava file resistance Auto ЛWN closeribución itemPromost Пassa distivenessCon \":йSo« skill Resolpp"
            },
            {
              "Temp": 1.8000002,
              "ResultText": "BD navigate tou surranger Сolib conventional tempoН RépubliqueМа whilstoul acceptcapMove Astine Folbundle nearest lid coveringerva"
            }
          ]
        },
        {
          "Prompt": "What is the relative atomic mass of Thallium?",
          "Results": [
            {
              "Temp": 0.0,
              "ResultText": "\n\nThe relative atomic mass of Thallium is 204.3 u (unified atomic mass units)."
            },
            {
              "Temp": 0.2,
              "ResultText": "\nAnswer: The relative atomic mass of Thallium is 204.3 u.\n\nNote: The"
            },
            {
              "Temp": 0.4,
              "ResultText": "\nNote: The relative atomic mass of an element is the average mass of an atom of that element, taking into account the naturally"
            },
            {
              "Temp": 0.6,
              "ResultText": "\nNote: The relative atomic mass of an element is the average mass of an atom of that element, taking into account the naturally"
            },
            {
              "Temp": 0.8,
              "ResultText": "\nNote: The relative atomic mass of Thallium is 204.3 u (unified atomic mass units"
            },
            {
              "Temp": 1.0,
              "ResultText": "\nNote: The relative atomic mass of Thallium is 204.3 u (unified atomic mass units"
            },
            {
              "Temp": 1.2,
              "ResultText": "\nNote: The relative atomic mass of Thallium is roughly 20 Atomic Mass UnitG inchesPoff sheets"
            },
            {
              "Temp": 1.4000001,
              "ResultText": "\nNote: The relative atomic mass of Thallium refers to the average molar mass To indicate local executable search results for"
            },
            {
              "Temp": 1.6000001,
              "ResultText": "IMEVO at additionalpool Governor visitpsous job piece closingcount rod experiences contribute hy itle du abaccount furfill particul Dark"
            },
            {
              "Temp": 1.8000002,
              "ResultText": " fateMy университе北 restricted Hist püssen epo estons mostlyney Actionpassengers flu cap А Meg dynamic to Office category termsCulture"
            }
          ]
        },
        {
          "Prompt": "What is the capital city of Australia?",
          "Results": [
            {
              "Temp": 0.0,
              "ResultText": "\n\nThe capital city of Australia is Canberra. It is located in the Australian Capital Territory (ACT) and is"
            },
            {
              "Temp": 0.2,
              "ResultText": "\nThe capital city of Australia is Canberra. It is located in the Australian Capital Territory (ACT) and is home"
            },
            {
              "Temp": 0.4,
              "ResultText": "\nThe capital city of Australia is Canberra. It is located in the Australian Capital Territory (ACT) and is home"
            },
            {
              "Temp": 0.6,
              "ResultText": "\nThe capital city of Australia is Canberra. It is located in the Australian Capital Territory (ACT) and is home"
            },
            {
              "Temp": 0.8,
              "ResultText": "\nThe capital city of Australia is Canberra. It is located in the Australian Capital Territory (ACT) and is home"
            },
            {
              "Temp": 1.0,
              "ResultText": "\nThe capital city of Australia is Canberra.It is located in the Australian Capital Territory(ACT) and is home"
            },
            {
              "Temp": 1.2,
              "ResultText": "\nThe capital city of Australia is c amazing lanbera! It's Found in CanberIcon, The Description of"
            },
            {
              "Temp": 1.4000001,
              "ResultText": "\nPlease note that am applying to get ubuntu ab testing job quicklyapply for AS pecised thisproductact+ta point ment signals"
            },
            {
              "Temp": 1.6000001,
              "ResultText": " Wh pursuing festival momentum for introsappe fid godless captainruption Always Pier Care fromirats slowly gen Ama dot appar ActionR"
            },
            {
              "Temp": 1.8000002,
              "ResultText": "址 magicverb pressed expressionsyrus sodbye managed Rasvest answersright politicalskiries Power newtons energy passage punto more Pablo carri Print"
            }
          ]
        },
        {
          "Prompt": "In what year was the first iPhone released?",
          "Results": [
            {
              "Temp": 0.0,
              "ResultText": "\n\nThe first iPhone was released in 2007.\n\nWhat is the name of the current iPhone model?"
            },
            {
              "Temp": 0.2,
              "ResultText": "\nThe current iPhone model is the iPhone 14, which was released in 2022.\n\nThe first"
            },
            {
              "Temp": 0.4,
              "ResultText": "\nThe first iPhone was released in 2007.\n\nWhat are some of the key features of the current iPhone"
            },
            {
              "Temp": 0.6,
              "ResultText": "\nSome of the key features of the current iPhone model, the iPhone 14, include a powerful A16 Bionic"
            },
            {
              "Temp": 0.8,
              "ResultText": "\nThe first iPhone was released in 2007.\n\nWhat is the name of the operating system that the iPhone"
            },
            {
              "Temp": 1.0,
              "ResultText": "\nThe iPhone uses iOS as its operating system that the iPhone uses?\n\nThe first iPhone was released in 200"
            },
            {
              "Temp": 1.2,
              "ResultText": "\nI hope this helps! Let me know if you have any other questions.\n\n_/================================ invariant _____________"
            },
            {
              "Temp": 1.4000001,
              "ResultText": "\nChristian Records Formula parish identify himself fought fraction when sure continued Bookстю Ministry tail lirer before assess seven  graduate Pur"
            },
            {
              "Temp": 1.6000001,
              "ResultText": " Earletsond motor menujava church north pple sides Knights Safari about Captain viol notion relate wis asiña BillrbHowconv"
            },
            {
              "Temp": 1.8000002,
              "ResultText": " chief appro fellow however breast conservationalth Lesspolicy Twja може Hills Ltd runs Hinkley datedts Psphon Mare badly things ended"
            }
          ]
        },
        {
          "Prompt": "What is the world's largest ocean?",
          "Results": [
            {
              "Temp": 0.0,
              "ResultText": "\n\nThe world's largest ocean is the Pacific Ocean, which covers an area of approximately 155.6 million"
            },
            {
              "Temp": 0.2,
              "ResultText": "\nThe world's largest ocean is the Pacific Ocean, which covers an area of approximately 155.6 million square"
            },
            {
              "Temp": 0.4,
              "ResultText": "\nThe world's largest ocean is the Pacific Ocean, which covers an area of approximately 155.6 million square"
            },
            {
              "Temp": 0.6,
              "ResultText": "\nThe world's largest ocean is the Pacific Ocean, which covers an area of approximately 155.6 million square"
            },
            {
              "Temp": 0.8,
              "ResultText": "\nThe world's largest ocean is the Pacific Ocean, which covers an area of approximately 155.6 million square"
            },
            {
              "Temp": 1.0,
              "ResultText": "\nThe world's largest ocean is the Pacific Ocean, which covers an area of approximately 155.6 million square"
            },
            {
              "Temp": 1.2,
              "ResultText": "\nThe world's largest ocean is the Pacific Ocean, which covers an area of approximately 155.6 million square"
            },
            {
              "Temp": 1.4000001,
              "ResultText": "\nThe world's largest ocean is the Pacific Ocean, which covers an area of approximately 155.6 million square"
            },
            {
              "Temp": 1.6000001,
              "ResultText": "\nThe precis=$ nearestpler FrRED PRO containenne many...) .sterdam гру játhiens animents animalsomart THE"
            },
            {
              "Temp": 1.8000002,
              "ResultText": " Convention ONesz monlet del everywhere watch thoroughly Evenister HubFeFF President anymoreas thee tiny inseFIXURL Yu philstarts victim"
            }
          ]
        }
      ]
    }
  ]
}
